index/__init__.py
index/__main__.py
index/chunk.py
index/cli.py
index/print_once.py
index/timer.py
index/db/__init__.py
index/index_001/__init__.py
index/index_001/format_xls.py
index/index_001/format_xlsb.py
index/index_001/format_xlsx.py
index/index_001/funcs.py
index-0.5.3.dev2.dist-info/entry_points.txt
index-0.5.3.dev2.dist-info/licenses/LICENSE.ru-RU.txt
index-0.5.3.dev2.dist-info/licenses/LICENSE.txt
index-0.5.3.dev2.dist-info/WHEEL
index-0.5.3.dev2.dist-info/METADATA
index-0.5.3.dev2.dist-info/RECORD
