Metadata-Version: 2.4
Name: index
Version: 0.5.3.dev2
Summary: A lightweight spreadsheet indexing system
Author-email: Stan Ovchinnikov <lishnih@gmail.com>
Requires-Python: >=3.6
License-Expression: MIT OR LGPL-2.1-or-later
Classifier: Development Status :: 4 - Beta
Classifier: Environment :: Console
Classifier: Intended Audience :: Manufacturing
Classifier: Operating System :: OS Independent
Classifier: Programming Language :: Python
Classifier: Topic :: Utilities
License-File: LICENSE.ru-RU.txt
License-File: LICENSE.txt
Requires-Dist: openpyxl>=3.0
Requires-Dist: pyxlsb>=1.0
Requires-Dist: pymongo>=4.0
Requires-Dist: index[obsolete] ; extra == "all"
Requires-Dist: index[dotenv] ; extra == "all"
Requires-Dist: python-dotenv ; extra == "dotenv"
Requires-Dist: xlrd ; extra == "obsolete"
Project-URL: Homepage, https://github.com/ndtfy/index.next
Project-URL: Issues, https://github.com/ndtfy/index.next/issues
Project-URL: Source, https://gitflic.ru/project/stan/index
Provides-Extra: all
Provides-Extra: dotenv
Provides-Extra: obsolete
